{
  "id": "3bcc9f5279a9d76bf9e5a6f10ca2697c34d65d40a9f6c6ad29927571a8438dfa",
  "title": "Altman dice \"no sé\" cuando le preguntan sobre salir a bolsa en 2026",
  "summary": "Altman dice \"no sé\" cuando le preguntan sobre salir a bolsa en 2026...",
  "url": "https://es.investing.com/news/stock-market-news/altman-dice-no-se-cuando-le-preguntan-sobre-salir-a-bolsa-en-2026-432si-3735880",
  "source": "Investing.com Mercados",
  "sourceUrl": "https://es.investing.com/rss/news_25.rss",
  "publishedAt": "2026-07-09T14:20:01.000Z",
  "imageUrl": "https://images.unsplash.com/photo-1544377193-33dcf4d68fb5?w=800&auto=format&fit=crop&q=80",
  "imageAlt": "Altman dice \"no sé\" cuando le preguntan sobre salir a bolsa en 2026",
  "tags": [
    "economia",
    "economia",
    "actualidad"
  ],
  "aiSummary": "Altman dice \"no sé\" cuando le preguntan sobre salir a bolsa en 2026...",
  "keyPoints": [
    "Altman dice \"no sé\" cuando le preguntan sobre salir a bolsa en 2026"
  ],
  "whyMatters": "Noticia de actualidad en el sector de economia.",
  "multimedia": [
    {
      "type": "image",
      "url": "https://images.unsplash.com/photo-1544377193-33dcf4d68fb5?w=800&auto=format&fit=crop&q=80",
      "alt": "Altman dice \"no sé\" cuando le preguntan sobre salir a bolsa en 2026",
      "caption": "Imagen de portada"
    }
  ],
  "subcategory": "Mercados",
  "hashtags": [
    "#Economia"
  ],
  "fullArticle": "Altman dice \"no sé\" cuando le preguntan sobre salir a bolsa en 2026...",
  "category": "economia",
  "scrapedAt": "2026-07-09T15:01:09.412Z",
  "links": [],
  "interestingData": [],
  "_tokens": {},
  "_numbers": {},
  "_trigrams": {}
}