{
  "id": "8137c2e1bad7d2ae863c9459f000b802cd08abbd8d47c7f2de0622a038a7da80",
  "title": "Iran war live: New attacks on Iran as US says talks still on",
  "summary": "Washington official says US not behind the latest strikes and that technical talks with Iran continue. ",
  "url": "https://www.aljazeera.com/news/liveblog/2026/7/10/iran-war-live-fresh-attacks-on-iran-as-us-says-talks-still-on",
  "source": "Al Jazeera English",
  "sourceUrl": "https://www.aljazeera.com/xml/rss/all.xml",
  "publishedAt": "2026-07-10T00:00:00.000Z",
  "imageUrl": "https://www.aljazeera.com/wp-content/uploads/2026/07/2026-07-09T190340Z_100459502_RC2HAMAIOJ0U_RTRMADP_3_IRAN-CRISIS-KHAMENEI-1783636785.jpg?resize=1920%2C1440",
  "imageAlt": "Iran war live: New attacks on Iran as US says talks still on",
  "tags": [
    "internacional",
    "internacional",
    "actualidad"
  ],
  "aiSummary": "Washington official says US not behind the latest strikes and that technical talks with Iran continue. ",
  "keyPoints": [
    "Iran war live: New attacks on Iran as US says talks still on"
  ],
  "whyMatters": "Noticia de actualidad en el sector de internacional.",
  "multimedia": [
    {
      "type": "image",
      "url": "https://www.aljazeera.com/wp-content/uploads/2026/07/2026-07-09T190340Z_100459502_RC2HAMAIOJ0U_RTRMADP_3_IRAN-CRISIS-KHAMENEI-1783636785.jpg?resize=1920%2C1440",
      "alt": "Iran war live: New attacks on Iran as US says talks still on",
      "caption": "Iran war live: New attacks on Iran as US says talks still on"
    }
  ],
  "subcategory": "europa/general",
  "hashtags": [
    "#Internacional"
  ],
  "fullArticle": "Washington official says US not behind the latest strikes and that technical talks with Iran continue. ...",
  "category": "internacional",
  "scrapedAt": "2026-07-10T01:23:50.583Z",
  "links": [],
  "interestingData": [],
  "_tokens": {},
  "_numbers": {},
  "_trigrams": {}
}