{
  "id": "8ef2d04baaa88122fd8a04fc010da49f3f8da7a0114bd3ac64fe36fb653d838b",
  "title": "Yen hits its weakest since 1986 ... where is the intervention Danger Zone? Chief Cabinet Secretary Kihara tried some verbal support, got ignored",
  "summary": "Funnily enough, this was on the charts the alst time yen was this weak....",
  "url": "https://www.forexlive.com/forex/yen-hits-its-weakest-since-1986-where-is-the-intervention-danger-zone-20260630/",
  "source": "Forexlive",
  "sourceUrl": "https://www.forexlive.com",
  "publishedAt": "2026-06-30T01:21:11.837Z",
  "imageUrl": "https://images.investinglive.com/images/usdyen%20intervention%20does%20not%20work%2030%20June%202026_id_793308d5-aed2-4895-b84f-5ea5bcd08326_size975.jpg",
  "imageAlt": "Yen hits its weakest since 1986 ... where is the intervention Danger Zone? Chief Cabinet Secretary Kihara tried some verbal support, got ignored",
  "tags": [
    "economia",
    "weakest",
    "intervention",
    "danger"
  ],
  "aiSummary": "Funnily enough, this was on the charts the alst time yen was this weak....",
  "keyPoints": [
    "Yen hits its weakest since 1986 ... where is the intervention Danger Zone? Chief Cabinet Secretary Kihara tried some verbal support, got ignored"
  ],
  "whyMatters": "Esta noticia representa un desarrollo relevante en su sector.",
  "multimedia": [
    {
      "type": "image",
      "url": "https://images.investinglive.com/images/usdyen%20intervention%20does%20not%20work%2030%20June%202026_id_793308d5-aed2-4895-b84f-5ea5bcd08326_size975.jpg",
      "alt": "Yen hits its weakest since 1986 ... where is the intervention Danger Zone? Chief Cabinet Secretary Kihara tried some verbal support, got ignored",
      "caption": "Imagen de portada del artículo"
    },
    {
      "type": "image",
      "url": "https://il.fm-atlas.com/cms/media/online-broker.jpg",
      "alt": "Yen hits its weakest since 1986 ... where is the intervention Danger Zone? Chief Cabinet Secretary Kihara tried some verbal support, got ignored",
      "caption": ""
    },
    {
      "type": "image",
      "url": "https://il.fm-atlas.com/cms/media/prop-broker-comparison.jpg",
      "alt": "Yen hits its weakest since 1986 ... where is the intervention Danger Zone? Chief Cabinet Secretary Kihara tried some verbal support, got ignored",
      "caption": ""
    }
  ],
  "subcategory": "Macroeconomia",
  "hashtags": [
    "#Weakest",
    "#Intervention",
    "#Danger"
  ],
  "fullArticle": "Funnily enough, this was on the charts the alst time yen was this weak....",
  "category": "economia",
  "scrapedAt": "2026-06-30T01:32:08.583Z",
  "links": [
    {
      "title": "Cobertura en Forexlive",
      "url": "https://www.google.com/search?q=Yen%20hits%20its%20weakest%20since%201986%20...%20where%20is%20the%20intervention%20Danger%20Zone%3F%20Chief%20Cabinet%20Secretary%20Kihara%20tried%20some%20verbal%20support%2C%20got%20ignored"
    },
    {
      "title": "Búsqueda en Wikipedia",
      "url": "https://es.wikipedia.org/wiki/Especial:Buscar?search=Yen%20hits%20its"
    }
  ],
  "interestingData": [
    {
      "label": "Impacto bursátil",
      "value": "Alto"
    },
    {
      "label": "Variación proyectada",
      "value": "+3.45%"
    },
    {
      "label": "Volumen operado",
      "value": "Mercado Mayorista"
    }
  ],
  "_tokens": {},
  "_numbers": {},
  "_trigrams": {}
}