{
  "id": "bb9ad2e1fb9c0fa4231030e61643389c3590064064aba18fa8da56cbe99781d6",
  "title": "have you ever hugged a tree? monsieur plant wraps sculptural human arms around trees",
  "summary": "<p>tree hug reflects on the relationship between time, landscape, and human presence.</p>\n<p>The post <a href=\"https://www.designboom.com/art/monsieur-plant-sculptural-human-arms-trees-tree-hug/\">have you ever hugged a tree? monsieur plant wraps sculptural human arms around trees</a> appeared first on <a href=\"https://www.designboom.com\">designboom | architecture & design magazine</a>.</p>\n",
  "url": "https://www.designboom.com/art/monsieur-plant-sculptural-human-arms-trees-tree-hug",
  "source": "Design Boom",
  "sourceUrl": "https://www.designboom.com/feed/",
  "publishedAt": "2026-07-09T14:30:24.000Z",
  "imageUrl": "https://images.unsplash.com/photo-1489599849927-2ee91cede3ba?w=800&auto=format&fit=crop&q=80",
  "imageAlt": "have you ever hugged a tree? monsieur plant wraps sculptural human arms around trees",
  "tags": [
    "cultura",
    "cultura",
    "actualidad"
  ],
  "aiSummary": "<p>tree hug reflects on the relationship between time, landscape, and human presence.</p>\n<p>The post <a href=\"https://www.designboom.com/art/monsieur-plant-sculptural-human-arms-trees-tree-hug/\">have you ever hugged a tree? monsieur plant wraps sculptural human arms around trees</a> appeared first on <a href=\"https://www.designboom.com\">designboom | architecture & design magazine</a>.</p>\n",
  "keyPoints": [
    "have you ever hugged a tree? monsieur plant wraps sculptural human arms around trees"
  ],
  "whyMatters": "Noticia de actualidad en el sector de cultura.",
  "multimedia": [
    {
      "type": "image",
      "url": "https://images.unsplash.com/photo-1489599849927-2ee91cede3ba?w=800&auto=format&fit=crop&q=80",
      "alt": "have you ever hugged a tree? monsieur plant wraps sculptural human arms around trees",
      "caption": "Imagen de portada"
    }
  ],
  "subcategory": "Arte",
  "hashtags": [
    "#Cultura"
  ],
  "fullArticle": "Created by artist Monsieur Plant, Tree Hug is an outdoor installation presented in the grounds of the Maison Chateaubriand in Châtenay-Malabry as part of the Jardins Ouverts festival in Paris and the Île-de-France region. The work consists of a sculptural pair of planted arms wrapped around a tree trunk, creating a visual connection between the human body and the natural environment.\n\nThrough this simple gesture of embrace, the installation explores themes of attachment, environmental awareness, and the relationship between humans and trees. By combining elements of sculpture and surrealism, Tree Hug transforms the tree into a figure of interaction, questioning the separation between natural and human forms.\n\nThe installation by French artist Christophe Guinet, known as Monsieur Plant, hig...",
  "category": "cultura",
  "scrapedAt": "2026-07-09T15:07:50.053Z",
  "links": [],
  "interestingData": [],
  "_tokens": {},
  "_numbers": {},
  "_trigrams": {}
}